[{"timestamp": "2026-05-22T00:00:11.441213", "channel": "street-roots-one", "endpoint": "street-roots-one", "event": "dial-outgoing"}, {"timestamp": "2026-05-22T00:00:11.924356", "channel": "street-roots-one", "endpoint": "street-roots-one", "event": "ivr"}, {"timestamp": "2026-05-22T00:00:11.999708", "channel": "street-roots-one", "endpoint": "street-roots-one", "event": "outgoing-streetroots"}, {"timestamp": "2026-05-22T00:00:14.085672", "channel": "street-roots-one", "endpoint": "street-roots-one", "event": "ivr"}, {"timestamp": "2026-05-22T00:00:14.362856", "channel": "street-roots-one", "endpoint": "street-roots-one", "event": "ivr"}, {"timestamp": "2026-05-22T00:00:14.381553", "channel": "street-roots-one", "endpoint": "street-roots-one", "event": "outgoing-dialtone"}, {"timestamp": "2026-05-22T00:00:25.165665", "channel": "street-roots-one", "endpoint": "street-roots-one", "event": "dial-outgoing"}, {"timestamp": "2026-05-22T00:00:25.367401", "channel": "street-roots-one", "endpoint": "street-roots-one", "event": "dial-pstn"}, {"timestamp": "2026-05-22T00:00:31.680726", "channel": "street-roots-one", "endpoint": "street-roots-one", "event": "outgoing-call"}, {"timestamp": "2026-05-22T00:00:31.885961", "channel": "street-roots-one", "endpoint": "street-roots-one", "event": "outgoing-dialstatus-no-answer"}, {"timestamp": "2026-05-22T00:00:39.957399", "channel": "street-roots-one", "endpoint": "street-roots-one", "event": "dial-outgoing"}, {"timestamp": "2026-05-22T00:00:40.398769", "channel": "street-roots-one", "endpoint": "street-roots-one", "event": "ivr"}, {"timestamp": "2026-05-22T00:00:40.413088", "channel": "street-roots-one", "endpoint": "street-roots-one", "event": "outgoing-streetroots"}, {"timestamp": "2026-05-22T00:00:42.598522", "channel": "street-roots-one", "endpoint": "street-roots-one", "event": "ivr"}, {"timestamp": "2026-05-22T00:00:42.725583", "channel": "street-roots-one", "endpoint": "street-roots-one", "event": "ivr"}, {"timestamp": "2026-05-22T00:00:42.741273", "channel": "street-roots-one", "endpoint": "street-roots-one", "event": "outgoing-dialtone"}, {"timestamp": "2026-05-22T00:00:54.007303", "channel": "hot-leet", "endpoint": "hot-leet", "event": "outgoing-call"}, {"timestamp": "2026-05-22T00:00:54.181184", "channel": "hot-leet", "endpoint": "hot-leet", "event": "outgoing-dialstatus-no-answer"}, {"timestamp": "2026-05-22T00:00:55.658056", "channel": "street-roots-one", "endpoint": "street-roots-one", "event": "dial-outgoing"}, {"timestamp": "2026-05-22T00:00:55.672558", "channel": "street-roots-one", "endpoint": "street-roots-one", "event": "dial-pstn"}, {"timestamp": "2026-05-22T00:00:56.920609", "channel": "%23", "endpoint": "%23", "event": "twilio-error-13224"}, {"timestamp": "2026-05-22T00:00:57.091154", "channel": "street-roots-one", "endpoint": "street-roots-one", "event": "outgoing-call"}, {"timestamp": "2026-05-22T00:00:57.112177", "channel": "street-roots-one", "endpoint": "street-roots-one", "event": "outgoing-dialstatus-failed"}, {"timestamp": "2026-05-22T00:00:57.141393", "channel": "street-roots-one", "endpoint": "street-roots-one", "event": "error-13224"}, {"timestamp": "2026-05-22T00:01:24.586055", "channel": "street-roots-one", "endpoint": "street-roots-one", "event": "dial-outgoing"}, {"timestamp": "2026-05-22T00:01:25.025757", "channel": "street-roots-one", "endpoint": "street-roots-one", "event": "ivr"}, {"timestamp": "2026-05-22T00:01:25.041414", "channel": "street-roots-one", "endpoint": "street-roots-one", "event": "outgoing-streetroots"}, {"timestamp": "2026-05-22T00:01:28.284219", "channel": "street-roots-one", "endpoint": "street-roots-one", "event": "ivr"}, {"timestamp": "2026-05-22T00:01:28.301414", "channel": "street-roots-one", "endpoint": "street-roots-one", "event": "outgoing-streetroots-menu"}, {"timestamp": "2026-05-22T00:01:33.841520", "channel": "street-roots-one", "endpoint": "street-roots-one", "event": "ivr"}, {"timestamp": "2026-05-22T00:01:34.135195", "channel": "street-roots-one", "endpoint": "street-roots-one", "event": "ivr"}, {"timestamp": "2026-05-22T00:01:34.150645", "channel": "street-roots-one", "endpoint": "street-roots-one", "event": "outgoing-dialtone"}, {"timestamp": "2026-05-22T00:01:49.803005", "channel": "street-roots-one", "endpoint": "street-roots-one", "event": "dial-outgoing"}, {"timestamp": "2026-05-22T00:01:50.131650", "channel": "street-roots-one", "endpoint": "street-roots-one", "event": "ivr"}, {"timestamp": "2026-05-22T00:01:50.146797", "channel": "street-roots-one", "endpoint": "street-roots-one", "event": "outgoing-streetroots"}, {"timestamp": "2026-05-22T00:01:53.316909", "channel": "street-roots-one", "endpoint": "street-roots-one", "event": "ivr"}, {"timestamp": "2026-05-22T00:01:53.331438", "channel": "street-roots-one", "endpoint": "street-roots-one", "event": "outgoing-streetroots-menu"}, {"timestamp": "2026-05-22T00:01:59.249487", "channel": "street-roots-one", "endpoint": "street-roots-one", "event": "ivr"}, {"timestamp": "2026-05-22T00:01:59.377968", "channel": "street-roots-one", "endpoint": "street-roots-one", "event": "ivr"}, {"timestamp": "2026-05-22T00:01:59.391272", "channel": "street-roots-one", "endpoint": "street-roots-one", "event": "outgoing-dialtone"}, {"timestamp": "2026-05-22T00:02:14.528895", "channel": "street-roots-one", "endpoint": "street-roots-one", "event": "dial-outgoing"}, {"timestamp": "2026-05-22T00:02:14.731160", "channel": "street-roots-one", "endpoint": "street-roots-one", "event": "dial-pstn"}, {"timestamp": "2026-05-22T00:02:45.543140", "channel": "street-roots-one", "endpoint": "street-roots-one", "event": "outgoing-call"}, {"timestamp": "2026-05-22T00:02:45.768539", "channel": "street-roots-one", "endpoint": "street-roots-one", "event": "outgoing-dialstatus-completed"}, {"timestamp": "2026-05-22T00:02:48.831613", "channel": "street-roots-one", "endpoint": "street-roots-one", "event": "dial-outgoing"}, {"timestamp": "2026-05-22T00:02:49.039809", "channel": "street-roots-one", "endpoint": "street-roots-one", "event": "ivr"}, {"timestamp": "2026-05-22T00:02:49.053690", "channel": "street-roots-one", "endpoint": "street-roots-one", "event": "outgoing-streetroots"}, {"timestamp": "2026-05-22T00:02:52.348526", "channel": "street-roots-one", "endpoint": "street-roots-one", "event": "ivr"}, {"timestamp": "2026-05-22T00:02:52.362641", "channel": "street-roots-one", "endpoint": "street-roots-one", "event": "outgoing-streetroots-menu"}, {"timestamp": "2026-05-22T00:02:55.608561", "channel": "street-roots-one", "endpoint": "street-roots-one", "event": "ivr"}, {"timestamp": "2026-05-22T00:02:55.774316", "channel": "street-roots-one", "endpoint": "street-roots-one", "event": "ivr"}, {"timestamp": "2026-05-22T00:02:55.788007", "channel": "street-roots-one", "endpoint": "street-roots-one", "event": "outgoing-dialtone"}, {"timestamp": "2026-05-22T00:03:06.016987", "channel": "street-roots-one", "endpoint": "street-roots-one", "event": "dial-outgoing"}, {"timestamp": "2026-05-22T00:03:06.190448", "channel": "street-roots-one", "endpoint": "street-roots-one", "event": "dial-pstn"}, {"timestamp": "2026-05-22T00:03:39.581156", "channel": "street-roots-one", "endpoint": "street-roots-one", "event": "outgoing-call"}, {"timestamp": "2026-05-22T00:03:39.771862", "channel": "street-roots-one", "endpoint": "street-roots-one", "event": "outgoing-dialstatus-completed"}, {"timestamp": "2026-05-22T00:03:46.467945", "channel": "street-roots-one", "endpoint": "street-roots-one", "event": "dial-outgoing"}, {"timestamp": "2026-05-22T00:03:46.838942", "channel": "street-roots-one", "endpoint": "street-roots-one", "event": "ivr"}, {"timestamp": "2026-05-22T00:03:46.861511", "channel": "street-roots-one", "endpoint": "street-roots-one", "event": "outgoing-streetroots"}, {"timestamp": "2026-05-22T00:03:50.185110", "channel": "street-roots-one", "endpoint": "street-roots-one", "event": "ivr"}, {"timestamp": "2026-05-22T00:03:50.201877", "channel": "street-roots-one", "endpoint": "street-roots-one", "event": "outgoing-streetroots-menu"}, {"timestamp": "2026-05-22T00:03:55.288514", "channel": "street-roots-one", "endpoint": "street-roots-one", "event": "ivr"}, {"timestamp": "2026-05-22T00:03:55.560498", "channel": "street-roots-one", "endpoint": "street-roots-one", "event": "ivr"}, {"timestamp": "2026-05-22T00:03:55.573277", "channel": "street-roots-one", "endpoint": "street-roots-one", "event": "outgoing-dialtone"}, {"timestamp": "2026-05-22T00:04:08.491039", "channel": "street-roots-one", "endpoint": "street-roots-one", "event": "dial-outgoing"}, {"timestamp": "2026-05-22T00:04:08.685278", "channel": "street-roots-one", "endpoint": "street-roots-one", "event": "dial-pstn"}, {"timestamp": "2026-05-22T00:04:33.548063", "channel": "street-roots-one", "endpoint": "street-roots-one", "event": "outgoing-call"}, {"timestamp": "2026-05-22T00:04:33.767463", "channel": "street-roots-one", "endpoint": "street-roots-one", "event": "outgoing-dialstatus-completed"}, {"timestamp": "2026-05-22T00:04:37.392230", "channel": "street-roots-one", "endpoint": "street-roots-one", "event": "dial-outgoing"}, {"timestamp": "2026-05-22T00:04:37.531864", "channel": "street-roots-one", "endpoint": "street-roots-one", "event": "ivr"}, {"timestamp": "2026-05-22T00:04:37.552923", "channel": "street-roots-one", "endpoint": "street-roots-one", "event": "outgoing-streetroots"}, {"timestamp": "2026-05-22T00:04:40.221924", "channel": "street-roots-one", "endpoint": "street-roots-one", "event": "ivr"}, {"timestamp": "2026-05-22T00:04:40.384777", "channel": "street-roots-one", "endpoint": "street-roots-one", "event": "ivr"}, {"timestamp": "2026-05-22T00:04:40.401946", "channel": "street-roots-one", "endpoint": "street-roots-one", "event": "outgoing-dialtone"}, {"timestamp": "2026-05-22T00:04:53.169497", "channel": "street-roots-one", "endpoint": "street-roots-one", "event": "dial-outgoing"}, {"timestamp": "2026-05-22T00:04:53.356480", "channel": "street-roots-one", "endpoint": "street-roots-one", "event": "dial-pstn"}, {"timestamp": "2026-05-22T00:04:54.730369", "channel": "street-roots-one", "endpoint": "street-roots-one", "event": "outgoing-call"}, {"timestamp": "2026-05-22T00:04:54.743029", "channel": "street-roots-one", "endpoint": "street-roots-one", "event": "outgoing-dialstatus-busy"}, {"timestamp": "2026-05-22T00:05:01.086569", "channel": "street-roots-one", "endpoint": "street-roots-one", "event": "dial-outgoing"}, {"timestamp": "2026-05-22T00:05:01.403309", "channel": "street-roots-one", "endpoint": "street-roots-one", "event": "ivr"}, {"timestamp": "2026-05-22T00:05:01.422010", "channel": "street-roots-one", "endpoint": "street-roots-one", "event": "outgoing-streetroots"}, {"timestamp": "2026-05-22T00:05:02.926943", "channel": "street-roots-one", "endpoint": "street-roots-one", "event": "ivr"}, {"timestamp": "2026-05-22T00:05:03.209512", "channel": "street-roots-one", "endpoint": "street-roots-one", "event": "ivr"}, {"timestamp": "2026-05-22T00:05:03.223593", "channel": "street-roots-one", "endpoint": "street-roots-one", "event": "outgoing-dialtone"}, {"timestamp": "2026-05-22T00:05:14.776003", "channel": "street-roots-one", "endpoint": "street-roots-one", "event": "dial-outgoing"}, {"timestamp": "2026-05-22T00:05:14.961389", "channel": "street-roots-one", "endpoint": "street-roots-one", "event": "dial-pstn"}, {"timestamp": "2026-05-22T00:05:19.591383", "channel": "street-roots-one", "endpoint": "street-roots-one", "event": "outgoing-call"}, {"timestamp": "2026-05-22T00:05:19.606200", "channel": "street-roots-one", "endpoint": "street-roots-one", "event": "outgoing-dialstatus-failed"}, {"timestamp": "2026-05-22T00:05:44.642165", "channel": "street-roots-one", "endpoint": "street-roots-one", "event": "dial-outgoing"}, {"timestamp": "2026-05-22T00:05:45.098182", "channel": "street-roots-one", "endpoint": "street-roots-one", "event": "ivr"}, {"timestamp": "2026-05-22T00:05:45.112477", "channel": "street-roots-one", "endpoint": "street-roots-one", "event": "outgoing-streetroots"}, {"timestamp": "2026-05-22T00:05:48.271850", "channel": "street-roots-one", "endpoint": "street-roots-one", "event": "ivr"}, {"timestamp": "2026-05-22T00:05:48.284970", "channel": "street-roots-one", "endpoint": "street-roots-one", "event": "outgoing-streetroots-menu"}, {"timestamp": "2026-05-22T00:05:58.200983", "channel": "street-roots-one", "endpoint": "street-roots-one", "event": "ivr"}, {"timestamp": "2026-05-22T00:05:58.620903", "channel": "street-roots-one", "endpoint": "street-roots-one", "event": "ivr"}, {"timestamp": "2026-05-22T00:05:58.641949", "channel": "street-roots-one", "endpoint": "street-roots-one", "event": "outgoing-dialtone"}, {"timestamp": "2026-05-22T00:06:11.691113", "channel": "street-roots-one", "endpoint": "street-roots-one", "event": "dial-outgoing"}, {"timestamp": "2026-05-22T00:06:11.863722", "channel": "street-roots-one", "endpoint": "street-roots-one", "event": "dial-pstn"}, {"timestamp": "2026-05-22T00:06:47.149891", "channel": "street-roots-one", "endpoint": "street-roots-one", "event": "outgoing-call"}, {"timestamp": "2026-05-22T00:06:47.386812", "channel": "street-roots-one", "endpoint": "street-roots-one", "event": "outgoing-dialstatus-no-answer"}, {"timestamp": "2026-05-22T00:10:46.143072", "channel": "microcosm", "endpoint": "microcosm", "event": "dial-outgoing"}, {"timestamp": "2026-05-22T00:10:46.500003", "channel": "microcosm", "endpoint": "microcosm", "event": "ivr"}, {"timestamp": "2026-05-22T00:10:46.513342", "channel": "microcosm", "endpoint": "microcosm", "event": "outgoing-portland"}, {"timestamp": "2026-05-22T00:10:49.731617", "channel": "microcosm", "endpoint": "microcosm", "event": "ivr"}, {"timestamp": "2026-05-22T00:10:49.744845", "channel": "microcosm", "endpoint": "microcosm", "event": "outgoing-portland-menu"}, {"timestamp": "2026-05-22T00:10:52.399862", "channel": "microcosm", "endpoint": "microcosm", "event": "ivr"}, {"timestamp": "2026-05-22T00:10:52.726267", "channel": "microcosm", "endpoint": "microcosm", "event": "ivr"}, {"timestamp": "2026-05-22T00:10:52.743294", "channel": "microcosm", "endpoint": "microcosm", "event": "outgoing-dialtone"}, {"timestamp": "2026-05-22T00:10:53.790712", "channel": "hot-leet", "endpoint": "hot-leet", "event": "outgoing-call"}, {"timestamp": "2026-05-22T00:10:53.804807", "channel": "hot-leet", "endpoint": "hot-leet", "event": "outgoing-dialstatus-no-answer"}, {"timestamp": "2026-05-22T00:11:03.844508", "channel": "microcosm", "endpoint": "microcosm", "event": "dial-outgoing"}, {"timestamp": "2026-05-22T00:11:04.057630", "channel": "microcosm", "endpoint": "microcosm", "event": "dial-pstn"}, {"timestamp": "2026-05-22T00:11:43.615282", "channel": "microcosm", "endpoint": "microcosm", "event": "outgoing-call"}, {"timestamp": "2026-05-22T00:11:43.828067", "channel": "microcosm", "endpoint": "microcosm", "event": "outgoing-dialstatus-completed"}, {"timestamp": "2026-05-22T00:12:24.359361", "channel": "microcosm", "endpoint": "microcosm", "event": "dial-outgoing"}, {"timestamp": "2026-05-22T00:12:24.673645", "channel": "microcosm", "endpoint": "microcosm", "event": "ivr"}, {"timestamp": "2026-05-22T00:12:24.697373", "channel": "microcosm", "endpoint": "microcosm", "event": "outgoing-portland"}, {"timestamp": "2026-05-22T00:12:26.702842", "channel": "microcosm", "endpoint": "microcosm", "event": "ivr"}, {"timestamp": "2026-05-22T00:12:26.977486", "channel": "microcosm", "endpoint": "microcosm", "event": "ivr"}, {"timestamp": "2026-05-22T00:12:26.995654", "channel": "microcosm", "endpoint": "microcosm", "event": "outgoing-dialtone"}, {"timestamp": "2026-05-22T00:12:38.126288", "channel": "microcosm", "endpoint": "microcosm", "event": "dial-outgoing"}, {"timestamp": "2026-05-22T00:12:38.351804", "channel": "microcosm", "endpoint": "microcosm", "event": "dial-pstn"}, {"timestamp": "2026-05-22T00:13:19.539724", "channel": "microcosm", "endpoint": "microcosm", "event": "outgoing-call"}, {"timestamp": "2026-05-22T00:13:19.733782", "channel": "microcosm", "endpoint": "microcosm", "event": "outgoing-dialstatus-completed"}, {"timestamp": "2026-05-22T00:17:40.398096", "channel": "microcosm", "endpoint": "microcosm", "event": "dial-outgoing"}, {"timestamp": "2026-05-22T00:17:40.739435", "channel": "microcosm", "endpoint": "microcosm", "event": "ivr"}, {"timestamp": "2026-05-22T00:17:40.754634", "channel": "microcosm", "endpoint": "microcosm", "event": "outgoing-portland"}, {"timestamp": "2026-05-22T00:17:42.830625", "channel": "microcosm", "endpoint": "microcosm", "event": "ivr"}, {"timestamp": "2026-05-22T00:17:42.985118", "channel": "microcosm", "endpoint": "microcosm", "event": "ivr"}, {"timestamp": "2026-05-22T00:17:43.004628", "channel": "microcosm", "endpoint": "microcosm", "event": "outgoing-dialtone"}, {"timestamp": "2026-05-22T00:17:54.552024", "channel": "microcosm", "endpoint": "microcosm", "event": "dial-outgoing"}, {"timestamp": "2026-05-22T00:17:54.730665", "channel": "microcosm", "endpoint": "microcosm", "event": "dial-pstn"}, {"timestamp": "2026-05-22T00:18:32.624648", "channel": "microcosm", "endpoint": "microcosm", "event": "outgoing-call"}, {"timestamp": "2026-05-22T00:18:32.838137", "channel": "microcosm", "endpoint": "microcosm", "event": "outgoing-dialstatus-completed"}, {"timestamp": "2026-05-22T00:20:53.865151", "channel": "hot-leet", "endpoint": "hot-leet", "event": "outgoing-call"}, {"timestamp": "2026-05-22T00:20:54.127083", "channel": "hot-leet", "endpoint": "hot-leet", "event": "outgoing-dialstatus-no-answer"}, {"timestamp": "2026-05-22T00:30:41.751017", "channel": "hot-leet", "endpoint": "hot-leet", "event": "outgoing-call"}, {"timestamp": "2026-05-22T00:30:42.028613", "channel": "hot-leet", "endpoint": "hot-leet", "event": "outgoing-dialstatus-failed"}, {"timestamp": "2026-05-22T00:30:42.044638", "channel": "hot-leet", "endpoint": "hot-leet", "event": "error-32011"}, {"timestamp": "2026-05-22T00:30:43.299573", "channel": "sips:microcosm", "endpoint": "sips:microcosm", "event": "twilio-error-32011"}, {"timestamp": "2026-05-22T00:31:14.922998", "channel": "hot-leet", "endpoint": "hot-leet", "event": "dial-sip-e164"}, {"timestamp": "2026-05-22T00:31:15.391393", "channel": "hot-leet", "endpoint": "hot-leet", "event": "dial-extension"}, {"timestamp": "2026-05-22T00:31:44.181739", "channel": "hot-leet", "endpoint": "hot-leet", "event": "outgoing-call"}, {"timestamp": "2026-05-22T00:31:44.434263", "channel": "hot-leet", "endpoint": "hot-leet", "event": "outgoing-dialstatus-no-answer"}, {"timestamp": "2026-05-22T00:35:19.582287", "channel": "ghost-mountain", "endpoint": "ghost-mountain", "event": "dial-outgoing"}, {"timestamp": "2026-05-22T00:35:20.101300", "channel": "ghost-mountain", "endpoint": "ghost-mountain", "event": "ivr"}, {"timestamp": "2026-05-22T00:35:20.113351", "channel": "ghost-mountain", "endpoint": "ghost-mountain", "event": "outgoing-portland"}, {"timestamp": "2026-05-22T00:35:23.503353", "channel": "ghost-mountain", "endpoint": "ghost-mountain", "event": "ivr"}, {"timestamp": "2026-05-22T00:35:23.521856", "channel": "ghost-mountain", "endpoint": "ghost-mountain", "event": "outgoing-portland-menu"}, {"timestamp": "2026-05-22T00:35:26.410876", "channel": "ghost-mountain", "endpoint": "ghost-mountain", "event": "ivr"}, {"timestamp": "2026-05-22T00:35:26.422817", "channel": "ghost-mountain", "endpoint": "ghost-mountain", "event": "outgoing-portland-menu"}, {"timestamp": "2026-05-22T00:38:43.383318", "channel": "street-roots-one", "endpoint": "street-roots-one", "event": "dial-outgoing"}, {"timestamp": "2026-05-22T00:38:43.873968", "channel": "street-roots-one", "endpoint": "street-roots-one", "event": "ivr"}, {"timestamp": "2026-05-22T00:38:43.887580", "channel": "street-roots-one", "endpoint": "street-roots-one", "event": "outgoing-streetroots"}, {"timestamp": "2026-05-22T00:38:45.627399", "channel": "street-roots-one", "endpoint": "street-roots-one", "event": "ivr"}, {"timestamp": "2026-05-22T00:38:45.642952", "channel": "street-roots-one", "endpoint": "street-roots-one", "event": "outgoing-streetroots-menu"}, {"timestamp": "2026-05-22T00:40:53.783899", "channel": "hot-leet", "endpoint": "hot-leet", "event": "outgoing-call"}, {"timestamp": "2026-05-22T00:40:54.002278", "channel": "hot-leet", "endpoint": "hot-leet", "event": "outgoing-dialstatus-no-answer"}, {"timestamp": "2026-05-22T00:44:10.765137", "channel": "microcosm", "endpoint": "microcosm", "event": "dial-outgoing"}, {"timestamp": "2026-05-22T00:44:11.181933", "channel": "microcosm", "endpoint": "microcosm", "event": "ivr"}, {"timestamp": "2026-05-22T00:44:11.194931", "channel": "microcosm", "endpoint": "microcosm", "event": "outgoing-portland"}, {"timestamp": "2026-05-22T00:44:12.809582", "channel": "microcosm", "endpoint": "microcosm", "event": "ivr"}, {"timestamp": "2026-05-22T00:44:12.989120", "channel": "microcosm", "endpoint": "microcosm", "event": "ivr"}, {"timestamp": "2026-05-22T00:44:13.004813", "channel": "microcosm", "endpoint": "microcosm", "event": "outgoing-dialtone"}, {"timestamp": "2026-05-22T00:44:22.454901", "channel": "microcosm", "endpoint": "microcosm", "event": "dial-outgoing"}, {"timestamp": "2026-05-22T00:44:22.629270", "channel": "microcosm", "endpoint": "microcosm", "event": "dial-pstn"}, {"timestamp": "2026-05-22T00:45:01.224628", "channel": "microcosm", "endpoint": "microcosm", "event": "outgoing-call"}, {"timestamp": "2026-05-22T00:45:01.431568", "channel": "microcosm", "endpoint": "microcosm", "event": "outgoing-dialstatus-completed"}, {"timestamp": "2026-05-22T00:45:02.662211", "channel": "microcosm", "endpoint": "microcosm", "event": "dial-outgoing"}, {"timestamp": "2026-05-22T00:45:02.815410", "channel": "microcosm", "endpoint": "microcosm", "event": "ivr"}, {"timestamp": "2026-05-22T00:45:02.845459", "channel": "microcosm", "endpoint": "microcosm", "event": "outgoing-portland"}, {"timestamp": "2026-05-22T00:45:05.685408", "channel": "microcosm", "endpoint": "microcosm", "event": "ivr"}, {"timestamp": "2026-05-22T00:45:05.704803", "channel": "microcosm", "endpoint": "microcosm", "event": "outgoing-portland-menu"}, {"timestamp": "2026-05-22T00:45:38.738221", "channel": "microcosm", "endpoint": "microcosm", "event": "dial-outgoing"}, {"timestamp": "2026-05-22T00:45:39.192530", "channel": "microcosm", "endpoint": "microcosm", "event": "ivr"}, {"timestamp": "2026-05-22T00:45:39.205228", "channel": "microcosm", "endpoint": "microcosm", "event": "outgoing-portland"}, {"timestamp": "2026-05-22T00:45:40.127831", "channel": "microcosm", "endpoint": "microcosm", "event": "ivr"}, {"timestamp": "2026-05-22T00:45:40.409414", "channel": "microcosm", "endpoint": "microcosm", "event": "ivr"}, {"timestamp": "2026-05-22T00:45:40.425246", "channel": "microcosm", "endpoint": "microcosm", "event": "outgoing-dialtone"}, {"timestamp": "2026-05-22T00:45:49.625390", "channel": "microcosm", "endpoint": "microcosm", "event": "dial-outgoing"}, {"timestamp": "2026-05-22T00:45:49.828121", "channel": "microcosm", "endpoint": "microcosm", "event": "dial-pstn"}, {"timestamp": "2026-05-22T00:48:30.206283", "channel": "microcosm", "endpoint": "microcosm", "event": "outgoing-call"}, {"timestamp": "2026-05-22T00:48:30.397221", "channel": "microcosm", "endpoint": "microcosm", "event": "outgoing-dialstatus-completed"}, {"timestamp": "2026-05-22T00:48:34.476757", "channel": "microcosm", "endpoint": "microcosm", "event": "dial-outgoing"}, {"timestamp": "2026-05-22T00:48:34.735718", "channel": "microcosm", "endpoint": "microcosm", "event": "ivr"}, {"timestamp": "2026-05-22T00:48:34.748049", "channel": "microcosm", "endpoint": "microcosm", "event": "outgoing-portland"}, {"timestamp": "2026-05-22T00:48:38.084568", "channel": "microcosm", "endpoint": "microcosm", "event": "ivr"}, {"timestamp": "2026-05-22T00:48:38.097198", "channel": "microcosm", "endpoint": "microcosm", "event": "outgoing-portland-menu"}, {"timestamp": "2026-05-22T00:48:39.290845", "channel": "microcosm", "endpoint": "microcosm", "event": "ivr"}, {"timestamp": "2026-05-22T00:48:39.552659", "channel": "microcosm", "endpoint": "microcosm", "event": "ivr"}, {"timestamp": "2026-05-22T00:48:39.566179", "channel": "microcosm", "endpoint": "microcosm", "event": "outgoing-dialtone"}, {"timestamp": "2026-05-22T00:48:54.085948", "channel": "microcosm", "endpoint": "microcosm", "event": "dial-outgoing"}, {"timestamp": "2026-05-22T00:48:54.287106", "channel": "microcosm", "endpoint": "microcosm", "event": "dial-pstn"}, {"timestamp": "2026-05-22T00:48:59.728757", "channel": "microcosm", "endpoint": "microcosm", "event": "outgoing-call"}, {"timestamp": "2026-05-22T00:48:59.746263", "channel": "microcosm", "endpoint": "microcosm", "event": "outgoing-dialstatus-completed"}, {"timestamp": "2026-05-22T00:49:23.568020", "channel": "clinton", "endpoint": "clinton", "event": "dial-outgoing"}, {"timestamp": "2026-05-22T00:49:24.051588", "channel": "clinton", "endpoint": "clinton", "event": "ivr"}, {"timestamp": "2026-05-22T00:49:24.067334", "channel": "clinton", "endpoint": "clinton", "event": "outgoing-portland"}, {"timestamp": "2026-05-22T00:49:24.683077", "channel": "microcosm", "endpoint": "microcosm", "event": "dial-outgoing"}, {"timestamp": "2026-05-22T00:49:24.964632", "channel": "microcosm", "endpoint": "microcosm", "event": "ivr"}, {"timestamp": "2026-05-22T00:49:24.986218", "channel": "microcosm", "endpoint": "microcosm", "event": "outgoing-portland"}, {"timestamp": "2026-05-22T00:49:27.334478", "channel": "clinton", "endpoint": "clinton", "event": "ivr"}, {"timestamp": "2026-05-22T00:49:27.350424", "channel": "clinton", "endpoint": "clinton", "event": "outgoing-portland-menu"}, {"timestamp": "2026-05-22T00:49:28.276561", "channel": "microcosm", "endpoint": "microcosm", "event": "ivr"}, {"timestamp": "2026-05-22T00:49:28.302534", "channel": "microcosm", "endpoint": "microcosm", "event": "outgoing-portland-menu"}, {"timestamp": "2026-05-22T00:49:28.828558", "channel": "microcosm", "endpoint": "microcosm", "event": "ivr"}, {"timestamp": "2026-05-22T00:49:29.097992", "channel": "microcosm", "endpoint": "microcosm", "event": "ivr"}, {"timestamp": "2026-05-22T00:49:29.112922", "channel": "microcosm", "endpoint": "microcosm", "event": "community-menu"}, {"timestamp": "2026-05-22T00:49:29.806769", "channel": "microcosm", "endpoint": "microcosm", "event": "ivr"}, {"timestamp": "2026-05-22T00:49:29.964573", "channel": "microcosm", "endpoint": "microcosm", "event": "ivr"}, {"timestamp": "2026-05-22T00:49:29.978820", "channel": "microcosm", "endpoint": "microcosm", "event": "robotron-menu"}, {"timestamp": "2026-05-22T00:49:30.380054", "channel": "microcosm", "endpoint": "microcosm", "event": "ivr"}, {"timestamp": "2026-05-22T00:49:30.528931", "channel": "microcosm", "endpoint": "microcosm", "event": "ivr"}, {"timestamp": "2026-05-22T00:49:30.546536", "channel": "microcosm", "endpoint": "microcosm", "event": "robotron-ninth-position"}, {"timestamp": "2026-05-22T00:49:37.405292", "channel": "clinton", "endpoint": "clinton", "event": "ivr"}, {"timestamp": "2026-05-22T00:49:37.713677", "channel": "clinton", "endpoint": "clinton", "event": "ivr"}, {"timestamp": "2026-05-22T00:49:37.728276", "channel": "clinton", "endpoint": "clinton", "event": "outgoing-dialtone"}, {"timestamp": "2026-05-22T00:49:40.355978", "channel": "microcosm", "endpoint": "microcosm", "event": "ivr"}, {"timestamp": "2026-05-22T00:49:40.610167", "channel": "microcosm", "endpoint": "microcosm", "event": "ivr"}, {"timestamp": "2026-05-22T00:49:40.626592", "channel": "microcosm", "endpoint": "microcosm", "event": "robotron-doctrine-of-futility"}, {"timestamp": "2026-05-22T00:49:43.686643", "channel": "microcosm", "endpoint": "microcosm", "event": "ivr"}, {"timestamp": "2026-05-22T00:49:43.723932", "channel": "microcosm", "endpoint": "microcosm", "event": "robotron-menu"}, {"timestamp": "2026-05-22T00:49:44.588493", "channel": "microcosm", "endpoint": "microcosm", "event": "dial-outgoing"}, {"timestamp": "2026-05-22T00:49:44.845846", "channel": "microcosm", "endpoint": "microcosm", "event": "ivr"}, {"timestamp": "2026-05-22T00:49:44.866583", "channel": "microcosm", "endpoint": "microcosm", "event": "outgoing-portland"}, {"timestamp": "2026-05-22T00:49:45.687239", "channel": "microcosm", "endpoint": "microcosm", "event": "ivr"}, {"timestamp": "2026-05-22T00:49:45.959001", "channel": "microcosm", "endpoint": "microcosm", "event": "ivr"}, {"timestamp": "2026-05-22T00:49:45.974104", "channel": "microcosm", "endpoint": "microcosm", "event": "outgoing-dialtone"}, {"timestamp": "2026-05-22T00:49:51.435420", "channel": "clinton", "endpoint": "clinton", "event": "dial-outgoing"}, {"timestamp": "2026-05-22T00:49:51.452551", "channel": "clinton", "endpoint": "clinton", "event": "dial-pstn"}, {"timestamp": "2026-05-22T00:49:58.516076", "channel": "microcosm", "endpoint": "microcosm", "event": "dial-outgoing"}, {"timestamp": "2026-05-22T00:49:58.692135", "channel": "microcosm", "endpoint": "microcosm", "event": "dial-pstn"}, {"timestamp": "2026-05-22T00:50:32.729478", "channel": "clinton", "endpoint": "clinton", "event": "outgoing-call"}, {"timestamp": "2026-05-22T00:50:32.920685", "channel": "clinton", "endpoint": "clinton", "event": "outgoing-dialstatus-completed"}, {"timestamp": "2026-05-22T00:50:53.930565", "channel": "hot-leet", "endpoint": "hot-leet", "event": "outgoing-call"}, {"timestamp": "2026-05-22T00:50:54.146364", "channel": "hot-leet", "endpoint": "hot-leet", "event": "outgoing-dialstatus-no-answer"}, {"timestamp": "2026-05-22T00:51:02.980555", "channel": "microcosm", "endpoint": "microcosm", "event": "outgoing-call"}, {"timestamp": "2026-05-22T00:51:03.149553", "channel": "microcosm", "endpoint": "microcosm", "event": "outgoing-dialstatus-completed"}, {"timestamp": "2026-05-22T00:51:03.401349", "channel": "mother-foucaults", "endpoint": "mother-foucaults", "event": "dial-outgoing"}, {"timestamp": "2026-05-22T00:51:03.550265", "channel": "mother-foucaults", "endpoint": "mother-foucaults", "event": "ivr"}, {"timestamp": "2026-05-22T00:51:03.566877", "channel": "mother-foucaults", "endpoint": "mother-foucaults", "event": "outgoing-motherfoucaults"}, {"timestamp": "2026-05-22T00:51:06.718036", "channel": "mother-foucaults", "endpoint": "mother-foucaults", "event": "ivr"}, {"timestamp": "2026-05-22T00:51:06.734872", "channel": "mother-foucaults", "endpoint": "mother-foucaults", "event": "outgoing-motherfoucaults-menu"}, {"timestamp": "2026-05-22T00:51:14.963304", "channel": "mother-foucaults", "endpoint": "mother-foucaults", "event": "ivr"}, {"timestamp": "2026-05-22T00:51:15.264249", "channel": "mother-foucaults", "endpoint": "mother-foucaults", "event": "ivr"}, {"timestamp": "2026-05-22T00:51:15.286099", "channel": "mother-foucaults", "endpoint": "mother-foucaults", "event": "utilities-portland"}, {"timestamp": "2026-05-22T00:51:15.809669", "channel": "mother-foucaults", "endpoint": "mother-foucaults", "event": "ivr"}, {"timestamp": "2026-05-22T00:51:16.080693", "channel": "mother-foucaults", "endpoint": "mother-foucaults", "event": "ivr"}, {"timestamp": "2026-05-22T00:51:16.096475", "channel": "mother-foucaults", "endpoint": "mother-foucaults", "event": "random-number"}, {"timestamp": "2026-05-22T00:51:30.375368", "channel": "mother-foucaults", "endpoint": "mother-foucaults", "event": "dial-outgoing"}, {"timestamp": "2026-05-22T00:51:30.837325", "channel": "mother-foucaults", "endpoint": "mother-foucaults", "event": "ivr"}, {"timestamp": "2026-05-22T00:51:30.860105", "channel": "mother-foucaults", "endpoint": "mother-foucaults", "event": "outgoing-motherfoucaults"}, {"timestamp": "2026-05-22T00:51:33.602255", "channel": "mother-foucaults", "endpoint": "mother-foucaults", "event": "ivr"}, {"timestamp": "2026-05-22T00:51:33.756485", "channel": "mother-foucaults", "endpoint": "mother-foucaults", "event": "ivr"}, {"timestamp": "2026-05-22T00:51:33.771766", "channel": "mother-foucaults", "endpoint": "mother-foucaults", "event": "outgoing-dialtone"}, {"timestamp": "2026-05-22T00:51:36.125160", "channel": "mother-foucaults", "endpoint": "mother-foucaults", "event": "dial-outgoing"}, {"timestamp": "2026-05-22T00:51:37.449599", "channel": "mother-foucaults", "endpoint": "mother-foucaults", "event": "dial-outgoing"}, {"timestamp": "2026-05-22T00:51:37.598833", "channel": "mother-foucaults", "endpoint": "mother-foucaults", "event": "ivr"}, {"timestamp": "2026-05-22T00:51:37.614168", "channel": "mother-foucaults", "endpoint": "mother-foucaults", "event": "outgoing-motherfoucaults"}, {"timestamp": "2026-05-22T00:51:39.540339", "channel": "mother-foucaults", "endpoint": "mother-foucaults", "event": "ivr"}, {"timestamp": "2026-05-22T00:51:39.677344", "channel": "mother-foucaults", "endpoint": "mother-foucaults", "event": "ivr"}, {"timestamp": "2026-05-22T00:51:39.699730", "channel": "mother-foucaults", "endpoint": "mother-foucaults", "event": "outgoing-dialtone"}, {"timestamp": "2026-05-22T00:51:52.715744", "channel": "mother-foucaults", "endpoint": "mother-foucaults", "event": "dial-outgoing"}, {"timestamp": "2026-05-22T00:51:52.926463", "channel": "mother-foucaults", "endpoint": "mother-foucaults", "event": "dial-pstn"}, {"timestamp": "2026-05-22T00:52:14.229898", "channel": "mother-foucaults", "endpoint": "mother-foucaults", "event": "outgoing-call"}, {"timestamp": "2026-05-22T00:52:14.415494", "channel": "mother-foucaults", "endpoint": "mother-foucaults", "event": "outgoing-dialstatus-no-answer"}, {"timestamp": "2026-05-22T00:52:15.429346", "channel": "mother-foucaults", "endpoint": "mother-foucaults", "event": "dial-outgoing"}, {"timestamp": "2026-05-22T00:52:15.579266", "channel": "mother-foucaults", "endpoint": "mother-foucaults", "event": "ivr"}, {"timestamp": "2026-05-22T00:52:15.592109", "channel": "mother-foucaults", "endpoint": "mother-foucaults", "event": "outgoing-motherfoucaults"}, {"timestamp": "2026-05-22T00:52:18.181109", "channel": "mother-foucaults", "endpoint": "mother-foucaults", "event": "ivr"}, {"timestamp": "2026-05-22T00:52:18.333242", "channel": "mother-foucaults", "endpoint": "mother-foucaults", "event": "ivr"}, {"timestamp": "2026-05-22T00:52:18.360557", "channel": "mother-foucaults", "endpoint": "mother-foucaults", "event": "outgoing-dialtone"}, {"timestamp": "2026-05-22T00:52:29.833710", "channel": "mother-foucaults", "endpoint": "mother-foucaults", "event": "dial-outgoing"}, {"timestamp": "2026-05-22T00:52:30.011759", "channel": "mother-foucaults", "endpoint": "mother-foucaults", "event": "dial-pstn"}, {"timestamp": "2026-05-22T00:52:30.933891", "channel": "mother-foucaults", "endpoint": "mother-foucaults", "event": "dial-outgoing"}, {"timestamp": "2026-05-22T00:52:31.069596", "channel": "mother-foucaults", "endpoint": "mother-foucaults", "event": "ivr"}, {"timestamp": "2026-05-22T00:52:31.097813", "channel": "mother-foucaults", "endpoint": "mother-foucaults", "event": "outgoing-motherfoucaults"}, {"timestamp": "2026-05-22T00:52:33.163389", "channel": "mother-foucaults", "endpoint": "mother-foucaults", "event": "ivr"}, {"timestamp": "2026-05-22T00:52:33.302015", "channel": "mother-foucaults", "endpoint": "mother-foucaults", "event": "ivr"}, {"timestamp": "2026-05-22T00:52:33.314176", "channel": "mother-foucaults", "endpoint": "mother-foucaults", "event": "outgoing-dialtone"}, {"timestamp": "2026-05-22T00:52:44.227257", "channel": "mother-foucaults", "endpoint": "mother-foucaults", "event": "dial-outgoing"}, {"timestamp": "2026-05-22T00:52:44.433392", "channel": "mother-foucaults", "endpoint": "mother-foucaults", "event": "dial-pstn"}, {"timestamp": "2026-05-22T00:53:11.995896", "channel": "mother-foucaults", "endpoint": "mother-foucaults", "event": "outgoing-call"}, {"timestamp": "2026-05-22T00:53:12.191508", "channel": "mother-foucaults", "endpoint": "mother-foucaults", "event": "outgoing-dialstatus-completed"}, {"timestamp": "2026-05-22T00:53:17.804880", "channel": "mother-foucaults", "endpoint": "mother-foucaults", "event": "dial-outgoing"}, {"timestamp": "2026-05-22T00:53:18.058496", "channel": "mother-foucaults", "endpoint": "mother-foucaults", "event": "ivr"}, {"timestamp": "2026-05-22T00:53:18.071803", "channel": "mother-foucaults", "endpoint": "mother-foucaults", "event": "outgoing-motherfoucaults"}, {"timestamp": "2026-05-22T00:53:20.321541", "channel": "mother-foucaults", "endpoint": "mother-foucaults", "event": "ivr"}, {"timestamp": "2026-05-22T00:53:20.589138", "channel": "mother-foucaults", "endpoint": "mother-foucaults", "event": "ivr"}, {"timestamp": "2026-05-22T00:53:20.607643", "channel": "mother-foucaults", "endpoint": "mother-foucaults", "event": "outgoing-dialtone"}, {"timestamp": "2026-05-22T00:53:33.699999", "channel": "mother-foucaults", "endpoint": "mother-foucaults", "event": "dial-outgoing"}, {"timestamp": "2026-05-22T00:53:33.887195", "channel": "mother-foucaults", "endpoint": "mother-foucaults", "event": "dial-pstn"}, {"timestamp": "2026-05-22T00:54:05.308245", "channel": "mother-foucaults", "endpoint": "mother-foucaults", "event": "outgoing-call"}, {"timestamp": "2026-05-22T00:54:05.528160", "channel": "mother-foucaults", "endpoint": "mother-foucaults", "event": "outgoing-dialstatus-busy"}, {"timestamp": "2026-05-22T00:54:11.357547", "channel": "mother-foucaults", "endpoint": "mother-foucaults", "event": "dial-outgoing"}, {"timestamp": "2026-05-22T00:54:11.627430", "channel": "mother-foucaults", "endpoint": "mother-foucaults", "event": "ivr"}, {"timestamp": "2026-05-22T00:54:11.648106", "channel": "mother-foucaults", "endpoint": "mother-foucaults", "event": "outgoing-motherfoucaults"}, {"timestamp": "2026-05-22T00:54:14.082202", "channel": "mother-foucaults", "endpoint": "mother-foucaults", "event": "ivr"}, {"timestamp": "2026-05-22T00:54:14.233058", "channel": "mother-foucaults", "endpoint": "mother-foucaults", "event": "ivr"}, {"timestamp": "2026-05-22T00:54:14.248194", "channel": "mother-foucaults", "endpoint": "mother-foucaults", "event": "outgoing-dialtone"}, {"timestamp": "2026-05-22T00:54:25.186542", "channel": "mother-foucaults", "endpoint": "mother-foucaults", "event": "dial-outgoing"}, {"timestamp": "2026-05-22T00:54:25.517705", "channel": "mother-foucaults", "endpoint": "mother-foucaults", "event": "reject"}, {"timestamp": "2026-05-22T00:54:29.109822", "channel": "mother-foucaults", "endpoint": "mother-foucaults", "event": "dial-outgoing"}, {"timestamp": "2026-05-22T00:54:29.373193", "channel": "mother-foucaults", "endpoint": "mother-foucaults", "event": "ivr"}, {"timestamp": "2026-05-22T00:54:29.388480", "channel": "mother-foucaults", "endpoint": "mother-foucaults", "event": "outgoing-motherfoucaults"}, {"timestamp": "2026-05-22T00:54:31.002004", "channel": "mother-foucaults", "endpoint": "mother-foucaults", "event": "ivr"}, {"timestamp": "2026-05-22T00:54:31.261989", "channel": "mother-foucaults", "endpoint": "mother-foucaults", "event": "ivr"}, {"timestamp": "2026-05-22T00:54:31.275395", "channel": "mother-foucaults", "endpoint": "mother-foucaults", "event": "outgoing-dialtone"}, {"timestamp": "2026-05-22T00:54:40.264426", "channel": "mother-foucaults", "endpoint": "mother-foucaults", "event": "dial-outgoing"}, {"timestamp": "2026-05-22T00:54:40.433911", "channel": "mother-foucaults", "endpoint": "mother-foucaults", "event": "dial-pstn"}, {"timestamp": "2026-05-22T00:56:04.253445", "channel": "mother-foucaults", "endpoint": "mother-foucaults", "event": "outgoing-call"}, {"timestamp": "2026-05-22T00:56:04.486073", "channel": "mother-foucaults", "endpoint": "mother-foucaults", "event": "outgoing-dialstatus-completed"}, {"timestamp": "2026-05-22T01:00:33.830050", "channel": "hot-leet", "endpoint": "hot-leet", "event": "outgoing-call"}, {"timestamp": "2026-05-22T01:00:34.066239", "channel": "hot-leet", "endpoint": "hot-leet", "event": "outgoing-dialstatus-no-answer"}, {"timestamp": "2026-05-22T01:00:34.080984", "channel": "hot-leet", "endpoint": "hot-leet", "event": "error-32009"}, {"timestamp": "2026-05-22T01:00:35.240352", "channel": "seattle-thistle", "endpoint": "seattle-thistle", "event": "twilio-error-32009"}, {"timestamp": "2026-05-22T01:00:51.354000", "channel": "hot-leet", "endpoint": "hot-leet", "event": "dial-sip-e164"}, {"timestamp": "2026-05-22T01:00:51.717396", "channel": "hot-leet", "endpoint": "hot-leet", "event": "dial-extension"}, {"timestamp": "2026-05-22T01:00:52.494513", "channel": "hot-leet", "endpoint": "hot-leet", "event": "outgoing-call"}, {"timestamp": "2026-05-22T01:00:52.511770", "channel": "hot-leet", "endpoint": "hot-leet", "event": "outgoing-dialstatus-no-answer"}, {"timestamp": "2026-05-22T01:02:53.600561", "channel": "microcosm", "endpoint": "microcosm", "event": "dial-outgoing"}, {"timestamp": "2026-05-22T01:02:53.962983", "channel": "microcosm", "endpoint": "microcosm", "event": "ivr"}, {"timestamp": "2026-05-22T01:02:53.995019", "channel": "microcosm", "endpoint": "microcosm", "event": "outgoing-portland"}, {"timestamp": "2026-05-22T01:02:54.757894", "channel": "microcosm", "endpoint": "microcosm", "event": "ivr"}, {"timestamp": "2026-05-22T01:02:55.043530", "channel": "microcosm", "endpoint": "microcosm", "event": "ivr"}, {"timestamp": "2026-05-22T01:02:55.060287", "channel": "microcosm", "endpoint": "microcosm", "event": "outgoing-dialtone"}, {"timestamp": "2026-05-22T01:03:05.222664", "channel": "microcosm", "endpoint": "microcosm", "event": "dial-outgoing"}, {"timestamp": "2026-05-22T01:03:05.433769", "channel": "microcosm", "endpoint": "microcosm", "event": "dial-pstn"}, {"timestamp": "2026-05-22T01:03:30.280884", "channel": "ainsworth", "endpoint": "ainsworth", "event": "dial-outgoing"}, {"timestamp": "2026-05-22T01:03:30.607746", "channel": "ainsworth", "endpoint": "ainsworth", "event": "ivr"}, {"timestamp": "2026-05-22T01:03:30.622710", "channel": "ainsworth", "endpoint": "ainsworth", "event": "outgoing-portland"}, {"timestamp": "2026-05-22T01:03:33.811588", "channel": "ainsworth", "endpoint": "ainsworth", "event": "ivr"}, {"timestamp": "2026-05-22T01:03:33.826873", "channel": "ainsworth", "endpoint": "ainsworth", "event": "outgoing-portland-menu"}, {"timestamp": "2026-05-22T01:03:37.321483", "channel": "microcosm", "endpoint": "microcosm", "event": "outgoing-call"}, {"timestamp": "2026-05-22T01:03:37.360234", "channel": "microcosm", "endpoint": "microcosm", "event": "outgoing-dialstatus-completed"}, {"timestamp": "2026-05-22T01:03:38.227579", "channel": "ainsworth", "endpoint": "ainsworth", "event": "ivr"}, {"timestamp": "2026-05-22T01:03:38.372436", "channel": "ainsworth", "endpoint": "ainsworth", "event": "ivr"}, {"timestamp": "2026-05-22T01:03:38.386915", "channel": "ainsworth", "endpoint": "ainsworth", "event": "dial-sip-asterisk"}, {"timestamp": "2026-05-22T01:03:39+00:00", "channel": "ainsworth", "endpoint": "ainsworth", "event": "voicemail-outgoing"}, {"timestamp": "2026-05-22T01:03:40+00:00", "channel": "ainsworth", "endpoint": "ainsworth", "event": "voicemail-outgoing"}, {"timestamp": "2026-05-22T01:03:43+00:00", "channel": "ainsworth", "endpoint": "ainsworth", "event": "voicemail-outgoing"}, {"timestamp": "2026-05-22T01:03:45+00:00", "channel": "ainsworth", "endpoint": "ainsworth", "event": "voicemail-create"}, {"timestamp": "2026-05-22T01:03:46+00:00", "channel": "ainsworth", "endpoint": "ainsworth", "event": "voicemail-create"}, {"timestamp": "2026-05-22T01:03:47+00:00", "channel": "ainsworth", "endpoint": "ainsworth", "event": "voicemail-create"}, {"timestamp": "2026-05-22T01:05:12.533381", "channel": "street-roots-one", "endpoint": "street-roots-one", "event": "dial-outgoing"}, {"timestamp": "2026-05-22T01:05:13.019443", "channel": "street-roots-one", "endpoint": "street-roots-one", "event": "ivr"}, {"timestamp": "2026-05-22T01:05:13.039823", "channel": "street-roots-one", "endpoint": "street-roots-one", "event": "outgoing-streetroots"}, {"timestamp": "2026-05-22T01:05:14.574206", "channel": "street-roots-one", "endpoint": "street-roots-one", "event": "ivr"}, {"timestamp": "2026-05-22T01:05:14.589607", "channel": "street-roots-one", "endpoint": "street-roots-one", "event": "outgoing-streetroots-menu"}, {"timestamp": "2026-05-22T01:05:15.165676", "channel": "street-roots-one", "endpoint": "street-roots-one", "event": "dial-outgoing"}, {"timestamp": "2026-05-22T01:05:15.334425", "channel": "street-roots-one", "endpoint": "street-roots-one", "event": "ivr"}, {"timestamp": "2026-05-22T01:05:15.348087", "channel": "street-roots-one", "endpoint": "street-roots-one", "event": "outgoing-streetroots"}, {"timestamp": "2026-05-22T01:05:17.845073", "channel": "street-roots-one", "endpoint": "street-roots-one", "event": "ivr"}, {"timestamp": "2026-05-22T01:05:17.859842", "channel": "street-roots-one", "endpoint": "street-roots-one", "event": "outgoing-streetroots-menu"}, {"timestamp": "2026-05-22T01:05:20.580907", "channel": "street-roots-one", "endpoint": "street-roots-one", "event": "dial-outgoing"}, {"timestamp": "2026-05-22T01:05:20.840757", "channel": "street-roots-one", "endpoint": "street-roots-one", "event": "ivr"}, {"timestamp": "2026-05-22T01:05:20.859761", "channel": "street-roots-one", "endpoint": "street-roots-one", "event": "outgoing-streetroots"}, {"timestamp": "2026-05-22T01:05:22.672937", "channel": "street-roots-one", "endpoint": "street-roots-one", "event": "ivr"}, {"timestamp": "2026-05-22T01:05:22.687630", "channel": "street-roots-one", "endpoint": "street-roots-one", "event": "outgoing-streetroots-menu"}, {"timestamp": "2026-05-22T01:10:34.097025", "channel": "hot-leet", "endpoint": "hot-leet", "event": "outgoing-call"}, {"timestamp": "2026-05-22T01:10:34.153957", "channel": "seattle-thistle", "endpoint": "seattle-thistle", "event": "twilio-error-32009"}, {"timestamp": "2026-05-22T01:10:34.337607", "channel": "hot-leet", "endpoint": "hot-leet", "event": "outgoing-dialstatus-no-answer"}, {"timestamp": "2026-05-22T01:10:34.358497", "channel": "hot-leet", "endpoint": "hot-leet", "event": "error-32009"}, {"timestamp": "2026-05-22T01:12:46.274173", "channel": "mother-foucaults", "endpoint": "mother-foucaults", "event": "dial-outgoing"}, {"timestamp": "2026-05-22T01:12:46.802515", "channel": "mother-foucaults", "endpoint": "mother-foucaults", "event": "ivr"}, {"timestamp": "2026-05-22T01:12:46.815046", "channel": "mother-foucaults", "endpoint": "mother-foucaults", "event": "outgoing-motherfoucaults"}, {"timestamp": "2026-05-22T01:12:48.888011", "channel": "mother-foucaults", "endpoint": "mother-foucaults", "event": "ivr"}, {"timestamp": "2026-05-22T01:12:49.172430", "channel": "mother-foucaults", "endpoint": "mother-foucaults", "event": "ivr"}, {"timestamp": "2026-05-22T01:12:49.185297", "channel": "mother-foucaults", "endpoint": "mother-foucaults", "event": "outgoing-dialtone"}, {"timestamp": "2026-05-22T01:13:02.094838", "channel": "mother-foucaults", "endpoint": "mother-foucaults", "event": "dial-outgoing"}, {"timestamp": "2026-05-22T01:13:02.284259", "channel": "mother-foucaults", "endpoint": "mother-foucaults", "event": "dial-pstn"}, {"timestamp": "2026-05-22T01:13:15.630213", "channel": "mother-foucaults", "endpoint": "mother-foucaults", "event": "outgoing-call"}, {"timestamp": "2026-05-22T01:13:15.799603", "channel": "mother-foucaults", "endpoint": "mother-foucaults", "event": "outgoing-dialstatus-busy"}, {"timestamp": "2026-05-22T01:14:55.834918", "channel": "street-roots-one", "endpoint": "street-roots-one", "event": "dial-outgoing"}, {"timestamp": "2026-05-22T01:14:56.311196", "channel": "street-roots-one", "endpoint": "street-roots-one", "event": "ivr"}, {"timestamp": "2026-05-22T01:14:56.322811", "channel": "street-roots-one", "endpoint": "street-roots-one", "event": "outgoing-streetroots"}, {"timestamp": "2026-05-22T01:14:59.577324", "channel": "street-roots-one", "endpoint": "street-roots-one", "event": "ivr"}, {"timestamp": "2026-05-22T01:14:59.614817", "channel": "street-roots-one", "endpoint": "street-roots-one", "event": "outgoing-streetroots-menu"}, {"timestamp": "2026-05-22T01:15:00.461750", "channel": "street-roots-one", "endpoint": "street-roots-one", "event": "ivr"}, {"timestamp": "2026-05-22T01:15:00.613701", "channel": "street-roots-one", "endpoint": "street-roots-one", "event": "ivr"}, {"timestamp": "2026-05-22T01:15:00.625502", "channel": "street-roots-one", "endpoint": "street-roots-one", "event": "outgoing-dialtone"}, {"timestamp": "2026-05-22T01:15:14.319456", "channel": "street-roots-one", "endpoint": "street-roots-one", "event": "dial-outgoing"}, {"timestamp": "2026-05-22T01:15:14.504037", "channel": "street-roots-one", "endpoint": "street-roots-one", "event": "dial-pstn"}, {"timestamp": "2026-05-22T01:15:57.637034", "channel": "street-roots-one", "endpoint": "street-roots-one", "event": "outgoing-call"}, {"timestamp": "2026-05-22T01:15:57.876501", "channel": "street-roots-one", "endpoint": "street-roots-one", "event": "outgoing-dialstatus-completed"}, {"timestamp": "2026-05-22T01:20:34.037100", "channel": "seattle-thistle", "endpoint": "seattle-thistle", "event": "twilio-error-32009"}, {"timestamp": "2026-05-22T01:20:34.135746", "channel": "hot-leet", "endpoint": "hot-leet", "event": "outgoing-call"}, {"timestamp": "2026-05-22T01:20:34.476197", "channel": "hot-leet", "endpoint": "hot-leet", "event": "outgoing-dialstatus-no-answer"}, {"timestamp": "2026-05-22T01:20:34.516453", "channel": "hot-leet", "endpoint": "hot-leet", "event": "error-32009"}, {"timestamp": "2026-05-22T01:21:26.742005", "channel": "ghost-mountain", "endpoint": "ghost-mountain", "event": "dial-outgoing"}, {"timestamp": "2026-05-22T01:21:27.219499", "channel": "ghost-mountain", "endpoint": "ghost-mountain", "event": "ivr"}, {"timestamp": "2026-05-22T01:21:27.236238", "channel": "ghost-mountain", "endpoint": "ghost-mountain", "event": "outgoing-portland"}, {"timestamp": "2026-05-22T01:21:30.443273", "channel": "ghost-mountain", "endpoint": "ghost-mountain", "event": "ivr"}, {"timestamp": "2026-05-22T01:21:30.459346", "channel": "ghost-mountain", "endpoint": "ghost-mountain", "event": "outgoing-portland-menu"}, {"timestamp": "2026-05-22T01:21:35.656177", "channel": "ghost-mountain", "endpoint": "ghost-mountain", "event": "ivr"}, {"timestamp": "2026-05-22T01:21:35.675975", "channel": "ghost-mountain", "endpoint": "ghost-mountain", "event": "outgoing-portland-menu"}, {"timestamp": "2026-05-22T01:25:45.595163", "channel": "central", "endpoint": "central", "event": "dial-outgoing"}, {"timestamp": "2026-05-22T01:25:45.949380", "channel": "central", "endpoint": "central", "event": "ivr"}, {"timestamp": "2026-05-22T01:25:45.965754", "channel": "central", "endpoint": "central", "event": "outgoing-portland"}, {"timestamp": "2026-05-22T01:25:48.700647", "channel": "central", "endpoint": "central", "event": "ivr"}, {"timestamp": "2026-05-22T01:25:48.715012", "channel": "central", "endpoint": "central", "event": "outgoing-portland-menu"}, {"timestamp": "2026-05-22T01:27:20.194826", "channel": "mother-foucaults", "endpoint": "mother-foucaults", "event": "dial-outgoing"}, {"timestamp": "2026-05-22T01:27:20.553651", "channel": "mother-foucaults", "endpoint": "mother-foucaults", "event": "ivr"}, {"timestamp": "2026-05-22T01:27:20.574711", "channel": "mother-foucaults", "endpoint": "mother-foucaults", "event": "outgoing-motherfoucaults"}, {"timestamp": "2026-05-22T01:27:23.677985", "channel": "mother-foucaults", "endpoint": "mother-foucaults", "event": "ivr"}, {"timestamp": "2026-05-22T01:27:23.959264", "channel": "mother-foucaults", "endpoint": "mother-foucaults", "event": "ivr"}, {"timestamp": "2026-05-22T01:27:23.974611", "channel": "mother-foucaults", "endpoint": "mother-foucaults", "event": "outgoing-dialtone"}, {"timestamp": "2026-05-22T01:27:38.654744", "channel": "mother-foucaults", "endpoint": "mother-foucaults", "event": "dial-outgoing"}, {"timestamp": "2026-05-22T01:27:38.994025", "channel": "mother-foucaults", "endpoint": "mother-foucaults", "event": "reject"}, {"timestamp": "2026-05-22T01:30:43.394307", "channel": "hot-leet", "endpoint": "hot-leet", "event": "outgoing-call"}, {"timestamp": "2026-05-22T01:30:43.400446", "channel": "sips:central", "endpoint": "sips:central", "event": "twilio-error-32011"}, {"timestamp": "2026-05-22T01:30:43.669361", "channel": "hot-leet", "endpoint": "hot-leet", "event": "outgoing-dialstatus-failed"}, {"timestamp": "2026-05-22T01:30:43.682262", "channel": "hot-leet", "endpoint": "hot-leet", "event": "error-32011"}, {"timestamp": "2026-05-22T01:34:41.921320", "channel": "killingsworth", "endpoint": "killingsworth", "event": "dial-outgoing"}, {"timestamp": "2026-05-22T01:34:42.507426", "channel": "killingsworth", "endpoint": "killingsworth", "event": "ivr"}, {"timestamp": "2026-05-22T01:34:42.521548", "channel": "killingsworth", "endpoint": "killingsworth", "event": "outgoing-portland"}, {"timestamp": "2026-05-22T01:34:45.740287", "channel": "killingsworth", "endpoint": "killingsworth", "event": "ivr"}, {"timestamp": "2026-05-22T01:34:45.754525", "channel": "killingsworth", "endpoint": "killingsworth", "event": "outgoing-portland-menu"}]